{
  "words": [
    { "chinese": "第五", "en": "fifth", "es": "quinto", "pt": "quinto", "de": "fünfte", "ru": "пятый", "fr": "cinquième", "it": "quinto", "ar": "خامس" },
    { "chinese": "云", "en": "cloud", "es": "nube", "pt": "nuvem", "de": "Wolke", "ru": "облако", "fr": "nuage", "it": "nuvola", "ar": "سحابة" },
    { "chinese": "朵", "en": "measure word (flowers/clouds)", "es": "clasificador (flores/nubes)", "pt": "classificador (flores/nuvens)", "de": "Zählwort (Blumen/Wolken)", "ru": "счётное слово (цветы/облака)", "fr": "classificateur (fleurs/nuages)", "it": "classificatore (fiori/nuvole)", "ar": "أداة عد (للزهور/السحب)" },
    { "chinese": "阴", "en": "cloudy / shade", "es": "nublado / sombra", "pt": "nublado / sombra", "de": "bewölkt / Schatten", "ru": "пасмурный / тень", "fr": "nuageux / ombre", "it": "nuvoloso / ombra", "ar": "غائم / ظل" },
    { "chinese": "变", "en": "change", "es": "cambiar", "pt": "mudar / transformar", "de": "ändern / wechseln", "ru": "меняться / изменять", "fr": "changer", "it": "cambiare", "ar": "يتغير / يتبدل" },
    { "chinese": "化", "en": "change / transform", "es": "transformar / cambiar", "pt": "transformar / mudar", "de": "verwandeln / transformieren", "ru": "превращать / трансформировать", "fr": "transformer / changer", "it": "trasformare / cambiare", "ar": "يحول / يتحول" },
    { "chinese": "雨", "en": "rain", "es": "lluvia", "pt": "chuva", "de": "Regen", "ru": "дождь", "fr": "pluie", "it": "pioggia", "ar": "مطر" },
    { "chinese": "下雨", "en": "to rain", "es": "llover", "pt": "chover", "de": "regnen", "ru": "идти дождю", "fr": "pleuvoir", "it": "piovere", "ar": "يمطر" },
    { "chinese": "滴", "en": "drop", "es": "gota", "pt": "gota", "de": "Tropfen", "ru": "капля", "fr": "goutte", "it": "goccia", "ar": "قطرة" },
    { "chinese": "落", "en": "fall", "es": "caer", "pt": "cair", "de": "fallen", "ru": "падать", "fr": "tomber", "it": "cadere", "ar": "يسقط / يتساقط" },
    { "chinese": "湿", "en": "wet", "es": "mojado / húmedo", "pt": "molhado / úmido", "de": "nass / feucht", "ru": "мокрый / влажный", "fr": "mouillé / humide", "it": "bagnato / umido", "ar": "مبلل / رطب" },
    { "chinese": "伞", "en": "umbrella", "es": "paraguas", "pt": "guarda-chuva", "de": "Regenschirm", "ru": "зонтик", "fr": "parapluie", "it": "ombrello", "ar": "مظلة" },
    { "chinese": "把", "en": "measure word / hold", "es": "clasificador / sostener", "pt": "classificador / segurar", "de": "Zählwort / halten", "ru": "счётное слово / держать", "fr": "classificateur / tenir", "it": "classificatore / tenere", "ar": "أداة عد / يمسك" },
    { "chinese": "躲", "en": "hide / avoid", "es": "esconderse / evitar", "pt": "esconder-se / evitar", "de": "verstecken / vermeiden", "ru": "прятаться / избегать", "fr": "se cacher / éviter", "it": "nascondersi / evitare", "ar": "يختبئ / يتجنب" },
    { "chinese": "淋", "en": "pour / drench", "es": "empapar / mojar", "pt": "encharcar / molhar", "de": "durchnässen / gießen", "ru": "промокать / лить", "fr": "tremper / mouiller", "it": "inzuppare / bagnare", "ar": "يبلل / ينقع" },
    { "chinese": "跑步", "en": "run / jog", "es": "correr / trotar", "pt": "correr / trotar", "de": "laufen / joggen", "ru": "бегать / бег", "fr": "courir / jogger", "it": "correre / fare jogging", "ar": "يركض / يهرول" },
    { "chinese": "赶", "en": "rush / hurry", "es": "apresurarse / correr", "pt": "apressar-se / correr", "de": "eilen / sich beeilen", "ru": "торопиться / спешить", "fr": "se dépêcher / se presser", "it": "affrettarsi / sbrigarsi", "ar": "يتسرع / يسرع" },
    { "chinese": "紧", "en": "tight / urgent", "es": "apretado / urgente", "pt": "apertado / urgente", "de": "eng / dringend", "ru": "тесный / срочный", "fr": "serré / urgent", "it": "stretto / urgente", "ar": "ضيق / عاجل" },
    { "chinese": "屋", "en": "house / room", "es": "casa / habitación", "pt": "casa / quarto", "de": "Haus / Zimmer", "ru": "дом / комната", "fr": "maison / pièce", "it": "casa / stanza", "ar": "منزل / غرفة" },
    { "chinese": "房", "en": "room / house", "es": "habitación / casa", "pt": "quarto / casa", "de": "Zimmer / Haus", "ru": "комната / дом", "fr": "pièce / maison", "it": "stanza / casa", "ar": "غرفة / منزل" },
    { "chinese": "间", "en": "room / between", "es": "habitación / entre", "pt": "quarto / entre", "de": "Zimmer / zwischen", "ru": "комната / между", "fr": "pièce / entre", "it": "stanza / tra", "ar": "غرفة / بين" },
    { "chinese": "店", "en": "shop / store", "es": "tienda", "pt": "loja", "de": "Geschäft / Laden", "ru": "магазин / лавка", "fr": "boutique / magasin", "it": "negozio", "ar": "محل / دكان" },
    { "chinese": "商", "en": "business", "es": "negocio / comercio", "pt": "negócio / comércio", "de": "Geschäft / Handel", "ru": "бизнес / торговля", "fr": "commerce / affaires", "it": "commercio / affari", "ar": "تجارة / أعمال" },
    { "chinese": "卖", "en": "sell", "es": "vender", "pt": "vender", "de": "verkaufen", "ru": "продавать", "fr": "vendre", "it": "vendere", "ar": "يبيع" },
    { "chinese": "买", "en": "buy", "es": "comprar", "pt": "comprar", "de": "kaufen", "ru": "покупать", "fr": "acheter", "it": "comprare", "ar": "يشتري" },
    { "chinese": "需", "en": "need", "es": "necesitar", "pt": "precisar", "de": "brauchen / benötigen", "ru": "нуждаться / нужно", "fr": "avoir besoin", "it": "aver bisogno", "ar": "يحتاج" },
    { "chinese": "钱", "en": "money", "es": "dinero", "pt": "dinheiro", "de": "Geld", "ru": "деньги", "fr": "argent", "it": "soldi / denaro", "ar": "مال / نقود" },
    { "chinese": "块", "en": "piece / yuan", "es": "trozo / yuan", "pt": "pedaço / yuan", "de": "Stück / Yuan", "ru": "кусок / юань", "fr": "morceau / yuan", "it": "pezzo / yuan", "ar": "قطعة / يوان" },
    { "chinese": "元", "en": "yuan / dollar", "es": "yuan / dólar", "pt": "yuan / dólar", "de": "Yuan / Dollar", "ru": "юань / доллар", "fr": "yuan / dollar", "it": "yuan / dollaro", "ar": "يوان / دولار" },
    { "chinese": "便", "en": "convenient / cheap", "es": "conveniente / barato", "pt": "conveniente / barato", "de": "bequem / billig", "ru": "удобный / дешёвый", "fr": "pratique / bon marché", "it": "conveniente / economico", "ar": "مناسب / رخيص" },
    { "chinese": "宜", "en": "suitable / cheap", "es": "adecuado / barato", "pt": "adequado / barato", "de": "geeignet / billig", "ru": "подходящий / дешёвый", "fr": "convenable / bon marché", "it": "adatto / economico", "ar": "مناسب / رخيص" },
    { "chinese": "贵", "en": "expensive", "es": "caro", "pt": "caro", "de": "teuer", "ru": "дорогой", "fr": "cher", "it": "caro / costoso", "ar": "غالٍ / مكلف" },
    { "chinese": "付", "en": "pay", "es": "pagar", "pt": "pagar", "de": "zahlen / bezahlen", "ru": "платить", "fr": "payer", "it": "pagare", "ar": "يدفع" },
    { "chinese": "找", "en": "look for / give change", "es": "buscar / dar cambio", "pt": "procurar / dar troco", "de": "suchen / Wechselgeld geben", "ru": "искать / давать сдачу", "fr": "chercher / rendre la monnaie", "it": "cercare / dare il resto", "ar": "يبحث / يرد الباقي" },
    { "chinese": "收", "en": "receive", "es": "recibir", "pt": "receber", "de": "empfangen / erhalten", "ru": "получать / принимать", "fr": "recevoir", "it": "ricevere", "ar": "يستلم / يتلقى" },
    { "chinese": "拿", "en": "take / hold", "es": "tomar / sostener", "pt": "pegar / segurar", "de": "nehmen / halten", "ru": "брать / держать", "fr": "prendre / tenir", "it": "prendere / tenere", "ar": "يأخذ / يمسك" },
    { "chinese": "撑", "en": "support / open umbrella", "es": "sostener / abrir paraguas", "pt": "apoiar / abrir guarda-chuva", "de": "stützen / Schirm aufspannen", "ru": "поддерживать / раскрывать зонт", "fr": "soutenir / ouvrir un parapluie", "it": "sostenere / aprire l'ombrello", "ar": "يدعم / يفتح المظلة" },
    { "chinese": "继", "en": "continue", "es": "continuar", "pt": "continuar", "de": "fortsetzen / weiterführen", "ru": "продолжать", "fr": "continuer / poursuivre", "it": "continuare", "ar": "يواصل / يستمر" },
    { "chinese": "续", "en": "continue", "es": "continuar / seguir", "pt": "prosseguir / continuar", "de": "fortfahren / weitermachen", "ru": "продолжать / возобновлять", "fr": "continuer / reprendre", "it": "proseguire / continuare", "ar": "يستمر / يتابع" },
    { "chinese": "停", "en": "stop", "es": "parar / detenerse", "pt": "parar", "de": "anhalten / aufhören", "ru": "останавливаться / прекращать", "fr": "arrêter / s'arrêter", "it": "fermarsi / smettere", "ar": "يتوقف / يقف" },
    { "chinese": "止", "en": "stop / end", "es": "detener / terminar", "pt": "deter / encerrar", "de": "stoppen / enden", "ru": "прекращать / останавливать", "fr": "arrêter / mettre fin", "it": "fermare / terminare", "ar": "يوقف / ينهي" },
    { "chinese": "晴", "en": "clear / sunny", "es": "despejado / soleado", "pt": "claro / ensolarado", "de": "klar / sonnig", "ru": "ясный / солнечный", "fr": "clair / ensoleillé", "it": "sereno / soleggiato", "ar": "صحو / مشمس" },
    { "chinese": "朗", "en": "bright / clear", "es": "brillante / claro", "pt": "brilhante / claro", "de": "hell / klar", "ru": "светлый / ясный", "fr": "lumineux / clair", "it": "luminoso / chiaro", "ar": "مشرق / صافٍ" },
    { "chinese": "彩", "en": "color / colorful", "es": "color / colorido", "pt": "cor / colorido", "de": "Farbe / bunt", "ru": "цвет / красочный", "fr": "couleur / coloré", "it": "colore / colorato", "ar": "لون / ملوّن" },
    { "chinese": "虹", "en": "rainbow", "es": "arcoíris", "pt": "arco-íris", "de": "Regenbogen", "ru": "радуга", "fr": "arc-en-ciel", "it": "arcobaleno", "ar": "قوس قزح" },
    { "chinese": "道", "en": "road / way / measure word", "es": "camino / manera / clasificador", "pt": "estrada / forma / classificador", "de": "Weg / Art / Zählwort", "ru": "путь / способ / счётное слово", "fr": "chemin / voie / classificateur", "it": "strada / via / classificatore", "ar": "طريق / وسيلة / أداة عد" },
    { "chinese": "颜", "en": "color", "es": "color", "pt": "cor", "de": "Farbe", "ru": "цвет", "fr": "couleur", "it": "colore", "ar": "لون" },
    { "chinese": "紫", "en": "purple", "es": "morado / violeta", "pt": "roxo / violeta", "de": "lila / violett", "ru": "фиолетовый / пурпурный", "fr": "violet / mauve", "it": "viola / porpora", "ar": "بنفسجي" },
    { "chinese": "橙", "en": "orange", "es": "naranja", "pt": "laranja", "de": "orange", "ru": "оранжевый", "fr": "orange", "it": "arancione", "ar": "برتقالي" },
    { "chinese": "粉", "en": "pink / powder", "es": "rosa / polvo", "pt": "rosa / pó", "de": "rosa / Pulver", "ru": "розовый / порошок", "fr": "rose / poudre", "it": "rosa / polvere", "ar": "وردي / مسحوق" },
    { "chinese": "指", "en": "point / finger", "es": "señalar / dedo", "pt": "apontar / dedo", "de": "zeigen / Finger", "ru": "указывать / палец", "fr": "pointer / doigt", "it": "indicare / dito", "ar": "يشير / إصبع" },
    { "chinese": "叫喊", "en": "shout", "es": "gritar", "pt": "gritar", "de": "schreien / rufen", "ru": "кричать / вопить", "fr": "crier / appeler", "it": "gridare / urlare", "ar": "يصرخ / يصيح" },
    { "chinese": "惊", "en": "surprise", "es": "sorpresa / asustar", "pt": "surpresa / assustar", "de": "überraschen / erschrecken", "ru": "удивление / пугать", "fr": "surprendre / effrayer", "it": "sorprendere / spaventare", "ar": "مفاجأة / يفزع" },
    { "chinese": "喜", "en": "happy / like", "es": "feliz / gustar", "pt": "feliz / gostar", "de": "glücklich / mögen", "ru": "счастливый / любить", "fr": "heureux / aimer", "it": "felice / piacere", "ar": "سعيد / يحب" },
    { "chinese": "讶", "en": "surprised", "es": "sorprendido", "pt": "surpreso", "de": "überrascht", "ru": "удивлённый", "fr": "surpris / étonné", "it": "sorpreso / stupito", "ar": "مندهش / متفاجئ" },
    { "chinese": "奇", "en": "strange / wonderful", "es": "extraño / maravilloso", "pt": "estranho / maravilhoso", "de": "seltsam / wunderbar", "ru": "странный / удивительный", "fr": "étrange / merveilleux", "it": "strano / meraviglioso", "ar": "غريب / رائع" },
    { "chinese": "怪", "en": "strange / monster", "es": "extraño / monstruo", "pt": "estranho / monstro", "de": "seltsam / Monster", "ru": "странный / чудовище", "fr": "étrange / monstre", "it": "strano / mostro", "ar": "غريب / وحش" },
    { "chinese": "妙", "en": "wonderful", "es": "maravilloso / ingenioso", "pt": "maravilhoso / engenhoso", "de": "wunderbar / genial", "ru": "чудесный / восхитительный", "fr": "merveilleux / ingénieux", "it": "meraviglioso / ingegnoso", "ar": "رائع / بديع" },
    { "chinese": "极", "en": "extreme", "es": "extremo / extremadamente", "pt": "extremo / extremamente", "de": "extrem / äußerst", "ru": "крайний / чрезвычайно", "fr": "extrême / extrêmement", "it": "estremo / estremamente", "ar": "متطرف / للغاية" },
    { "chinese": "世", "en": "world / generation", "es": "mundo / generación", "pt": "mundo / geração", "de": "Welt / Generation", "ru": "мир / поколение", "fr": "monde / génération", "it": "mondo / generazione", "ar": "عالم / جيل" },
    { "chinese": "界", "en": "boundary / world", "es": "límite / mundo", "pt": "fronteira / mundo", "de": "Grenze / Welt", "ru": "граница / мир", "fr": "frontière / monde", "it": "confine / mondo", "ar": "حدود / عالم" },
    { "chinese": "原", "en": "original", "es": "original / primitivo", "pt": "original / primitivo", "de": "ursprünglich / original", "ru": "первоначальный / оригинальный", "fr": "original / primitif", "it": "originale / primitivo", "ar": "أصلي / أولي" },
    { "chinese": "神", "en": "god / magical", "es": "dios / mágico", "pt": "deus / mágico", "de": "Gott / magisch", "ru": "бог / магический", "fr": "dieu / magique", "it": "dio / magico", "ar": "إله / سحري" },
    { "chinese": "秘", "en": "secret", "es": "secreto", "pt": "segredo", "de": "Geheimnis / geheim", "ru": "тайна / секретный", "fr": "secret", "it": "segreto", "ar": "سر / سري" },
    { "chinese": "密", "en": "dense / secret", "es": "denso / secreto", "pt": "denso / secreto", "de": "dicht / geheim", "ru": "густой / тайный", "fr": "dense / secret", "it": "denso / segreto", "ar": "كثيف / سري" },
    { "chinese": "告", "en": "tell", "es": "decir / informar", "pt": "dizer / informar", "de": "sagen / mitteilen", "ru": "говорить / сообщать", "fr": "dire / informer", "it": "dire / informare", "ar": "يخبر / يبلغ" },
    { "chinese": "诉", "en": "tell", "es": "contar / relatar", "pt": "contar / relatar", "de": "erzählen / berichten", "ru": "рассказывать / говорить", "fr": "raconter / dire", "it": "raccontare / dire", "ar": "يحكي / يروي" },
    { "chinese": "故", "en": "old / reason", "es": "antiguo / razón", "pt": "antigo / razão", "de": "alt / Grund", "ru": "старый / причина", "fr": "ancien / raison", "it": "antico / motivo", "ar": "قديم / سبب" },
    { "chinese": "事", "en": "matter / thing", "es": "asunto / cosa", "pt": "assunto / coisa", "de": "Sache / Ding", "ru": "дело / вещь", "fr": "affaire / chose", "it": "faccenda / cosa", "ar": "أمر / شيء" },
    { "chinese": "情", "en": "feeling / situation", "es": "sentimiento / situación", "pt": "sentimento / situação", "de": "Gefühl / Situation", "ru": "чувство / ситуация", "fr": "sentiment / situation", "it": "sentimento / situazione", "ar": "شعور / وضع" },
    { "chinese": "讲", "en": "speak / tell", "es": "hablar / contar", "pt": "falar / contar", "de": "sprechen / erzählen", "ru": "говорить / рассказывать", "fr": "parler / raconter", "it": "parlare / raccontare", "ar": "يتكلم / يحكي" },
    { "chinese": "话", "en": "word / speech", "es": "palabra / discurso", "pt": "palavra / fala", "de": "Wort / Rede", "ru": "слово / речь", "fr": "mot / discours", "it": "parola / discorso", "ar": "كلمة / حديث" },
    { "chinese": "从", "en": "from", "es": "desde / de", "pt": "desde / de", "de": "von / seit", "ru": "от / с / из", "fr": "de / depuis", "it": "da / fin da", "ar": "من / منذ" },
    { "chinese": "久", "en": "long time", "es": "mucho tiempo", "pt": "muito tempo", "de": "lange Zeit", "ru": "долго / долгое время", "fr": "longtemps", "it": "molto tempo / a lungo", "ar": "وقت طويل / طويلاً" },
    { "chinese": "以前", "en": "before / ago", "es": "antes / hace", "pt": "antes / há", "de": "vorher / früher", "ru": "раньше / до", "fr": "avant / il y a", "it": "prima / fa", "ar": "قبل / منذ" },
    { "chinese": "古", "en": "ancient", "es": "antiguo", "pt": "antigo", "de": "antik / alt", "ru": "древний / старинный", "fr": "ancien / antique", "it": "antico", "ar": "قديم / عريق" },
    { "chinese": "传", "en": "pass / legend", "es": "pasar / leyenda", "pt": "passar / lenda", "de": "weitergeben / Legende", "ru": "передавать / легенда", "fr": "transmettre / légende", "it": "tramandare / leggenda", "ar": "ينقل / أسطورة" },
    { "chinese": "说", "en": "say / theory", "es": "decir / teoría", "pt": "dizer / teoria", "de": "sagen / Theorie", "ru": "говорить / теория", "fr": "dire / théorie", "it": "dire / teoria", "ar": "يقول / نظرية" },
    { "chinese": "据", "en": "according to", "es": "según", "pt": "segundo / de acordo com", "de": "laut / gemäß", "ru": "согласно / по", "fr": "selon / d'après", "it": "secondo / in base a", "ar": "وفقاً لـ / حسب" },
    { "chinese": "信", "en": "believe / letter", "es": "creer / carta", "pt": "acreditar / carta", "de": "glauben / Brief", "ru": "верить / письмо", "fr": "croire / lettre", "it": "credere / lettera", "ar": "يصدق / رسالة" },
    { "chinese": "相", "en": "mutual / appearance", "es": "mutuo / apariencia", "pt": "mútuo / aparência", "de": "gegenseitig / Aussehen", "ru": "взаимный / внешность", "fr": "mutuel / apparence", "it": "reciproco / apparenza", "ar": "متبادل / مظهر" },
    { "chinese": "仙", "en": "immortal / fairy", "es": "inmortal / hada", "pt": "imortal / fada", "de": "unsterblich / Fee", "ru": "бессмертный / фея", "fr": "immortel / fée", "it": "immortale / fata", "ar": "خالد / جنية" },
    { "chinese": "女仙", "en": "fairy / goddess", "es": "hada / diosa", "pt": "fada / deusa", "de": "Fee / Göttin", "ru": "фея / богиня", "fr": "fée / déesse", "it": "fata / dea", "ar": "جنية / إلهة" },
    { "chinese": "住在", "en": "live at", "es": "vivir en", "pt": "morar em / viver em", "de": "wohnen in / leben in", "ru": "жить в / проживать в", "fr": "habiter à / vivre à", "it": "abitare a / vivere a", "ar": "يسكن في / يقيم في" },
    { "chinese": "凡", "en": "mortal / ordinary", "es": "mortal / ordinario", "pt": "mortal / comum", "de": "sterblich / gewöhnlich", "ru": "смертный / обычный", "fr": "mortel / ordinaire", "it": "mortale / ordinario", "ar": "فانٍ / عادي" },
    { "chinese": "帮", "en": "help", "es": "ayudar", "pt": "ajudar", "de": "helfen", "ru": "помогать", "fr": "aider", "it": "aiutare", "ar": "يساعد" },
    { "chinese": "助", "en": "help / assist", "es": "ayudar / asistir", "pt": "ajudar / assistir", "de": "helfen / unterstützen", "ru": "помогать / содействовать", "fr": "aider / assister", "it": "aiutare / assistere", "ar": "يساعد / يعين" },
    { "chinese": "忙", "en": "busy", "es": "ocupado", "pt": "ocupado / atarefado", "de": "beschäftigt", "ru": "занятый", "fr": "occupé", "it": "occupato / indaffarato", "ar": "مشغول" },
    { "chinese": "善", "en": "good / kind", "es": "bueno / amable", "pt": "bom / bondoso", "de": "gut / freundlich", "ru": "добрый / хороший", "fr": "bon / aimable", "it": "buono / gentile", "ar": "طيب / لطيف" },
    { "chinese": "良", "en": "good / fine", "es": "bueno / fino", "pt": "bom / fino", "de": "gut / fein", "ru": "хороший / добросовестный", "fr": "bon / fin", "it": "buono / fine", "ar": "جيد / حسن" },
    { "chinese": "勇", "en": "brave", "es": "valiente", "pt": "corajoso / valente", "de": "mutig / tapfer", "ru": "храбрый / мужественный", "fr": "courageux / brave", "it": "coraggioso / valoroso", "ar": "شجاع" },
    { "chinese": "敢", "en": "dare", "es": "atreverse", "pt": "ousar / atrever-se", "de": "wagen / sich trauen", "ru": "осмеливаться / решаться", "fr": "oser / avoir le courage", "it": "osare / avere il coraggio", "ar": "يجرؤ / يتجرأ" },
    { "chinese": "救", "en": "save / rescue", "es": "salvar / rescatar", "pt": "salvar / resgatar", "de": "retten / befreien", "ru": "спасать", "fr": "sauver / secourir", "it": "salvare / soccorrere", "ar": "ينقذ / يغيث" },
    { "chinese": "命", "en": "life / fate", "es": "vida / destino", "pt": "vida / destino", "de": "Leben / Schicksal", "ru": "жизнь / судьба", "fr": "vie / destin", "it": "vita / destino", "ar": "حياة / قدر" },
    { "chinese": "保", "en": "protect", "es": "proteger", "pt": "proteger", "de": "schützen / beschützen", "ru": "защищать / охранять", "fr": "protéger", "it": "proteggere", "ar": "يحمي / يصون" },
    { "chinese": "护", "en": "protect / guard", "es": "proteger / guardar", "pt": "proteger / guardar", "de": "schützen / bewachen", "ru": "защищать / охранять", "fr": "protéger / garder", "it": "proteggere / custodire", "ar": "يحرس / يحمي" },
    { "chinese": "安", "en": "safe / peaceful", "es": "seguro / tranquilo", "pt": "seguro / tranquilo", "de": "sicher / friedlich", "ru": "безопасный / спокойный", "fr": "sûr / paisible", "it": "sicuro / pacifico", "ar": "آمن / هادئ" },
    { "chinese": "全", "en": "complete / safe", "es": "completo / seguro", "pt": "completo / seguro", "de": "vollständig / sicher", "ru": "полный / безопасный", "fr": "complet / sûr", "it": "completo / sicuro", "ar": "كامل / آمن" },
    { "chinese": "幸", "en": "lucky", "es": "afortunado / suertudo", "pt": "afortunado / sortudo", "de": "glücklich / vom Glück begünstigt", "ru": "удачливый / счастливый", "fr": "chanceux / fortuné", "it": "fortunato", "ar": "محظوظ / سعيد الحظ" },
    { "chinese": "福", "en": "blessing", "es": "bendición / buena fortuna", "pt": "bênção / boa fortuna", "de": "Segen / Glück", "ru": "благословение / счастье", "fr": "bénédiction / bonne fortune", "it": "benedizione / fortuna", "ar": "بركة / نعمة" }
  ]
}